notochoordinates/__init__.py
notochoordinates/_version.py
notochoordinates/_widget.py
notochoordinates/main.py
notochoordinates/napari.yaml
notochoordinates/_tests/__init__.py
notochoordinates/_tests/test_widget.py
notochoordinates-0.1.1.dist-info/licenses/LICENSE
notochoordinates-0.1.1.dist-info/METADATA
notochoordinates-0.1.1.dist-info/WHEEL
notochoordinates-0.1.1.dist-info/entry_points.txt
notochoordinates-0.1.1.dist-info/top_level.txt
notochoordinates-0.1.1.dist-info/RECORD
